odoo9_addon_donation-9.0.1.0.0.99.dev21-py2.7-nspkg.pth
odoo9_addon_donation-9.0.1.0.0.99.dev21.dist-info/DESCRIPTION.rst
odoo9_addon_donation-9.0.1.0.0.99.dev21.dist-info/METADATA
odoo9_addon_donation-9.0.1.0.0.99.dev21.dist-info/RECORD
odoo9_addon_donation-9.0.1.0.0.99.dev21.dist-info/WHEEL
odoo9_addon_donation-9.0.1.0.0.99.dev21.dist-info/metadata.json
odoo9_addon_donation-9.0.1.0.0.99.dev21.dist-info/namespace_packages.txt
odoo9_addon_donation-9.0.1.0.0.99.dev21.dist-info/top_level.txt
odoo_addons/donation/README.rst
odoo_addons/donation/__init__.py
odoo_addons/donation/__openerp__.py
odoo_addons/donation/post_install.py
odoo_addons/donation/demo/donation_demo.xml
odoo_addons/donation/i18n/de.po
odoo_addons/donation/i18n/fr.po
odoo_addons/donation/models/__init__.py
odoo_addons/donation/models/account.py
odoo_addons/donation/models/donation.py
odoo_addons/donation/models/donation_campaign.py
odoo_addons/donation/models/partner.py
odoo_addons/donation/models/users.py
odoo_addons/donation/report/__init__.py
odoo_addons/donation/report/donation_report.py
odoo_addons/donation/report/donation_report_view.xml
odoo_addons/donation/security/donation_security.xml
odoo_addons/donation/security/ir.model.access.csv
odoo_addons/donation/static/description/icon.png
odoo_addons/donation/tests/__init__.py
odoo_addons/donation/tests/test_donation.py
odoo_addons/donation/views/account.xml
odoo_addons/donation/views/donation.xml
odoo_addons/donation/views/donation_campaign.xml
odoo_addons/donation/views/partner.xml
odoo_addons/donation/views/users.xml
odoo_addons/donation/wizard/__init__.py
odoo_addons/donation/wizard/donation_validate.py
odoo_addons/donation/wizard/donation_validate_view.xml
odoo_addons/donation/wizard/tax_receipt_option_switch.py
odoo_addons/donation/wizard/tax_receipt_option_switch_view.xml
